{
    "DNDConfig": null,
    "_height_": {
        "type": "string",
        "value": "100%"
    },
    "_left_": {
        "type": "string",
        "value": "52%"
    },
    "_margin_": [
        0,
        0,
        0,
        0
    ],
    "_orientation_": 6,
    "_padding_": [
        0,
        0,
        0,
        0
    ],
    "_percent_": true,
    "_skin_": "s56527b3cb1a429e98b414863fab2297",
    "_top_": {
        "type": "string",
        "value": "0"
    },
    "_width_": {
        "type": "string",
        "value": "48%"
    },
    "allboxes": [],
    "autogrowmode": 0,
    "canUpdateUI": true,
    "children": [
        "lblPasswordPolicy",
        "lblPolicy1",
        "lblPolicy2",
        "lblPolicy3",
        "lblPolicy4",
        "lblPolicy5"
    ],
    "clipbounds": true,
    "containerweight": 100,
    "enablescrolling": true,
    "id": "flxPasswordPolicy",
    "info": null,
    "iscustomlayout": false,
    "isvisible": true,
    "kuid": "ub63a062ab0b429a800c3353a26b4dcd",
    "layouttype": 4,
    "name": "kony.ui.FlexContainer",
    "parent": "flxChangePassword",
    "pf": "userwidgetmodel",
    "retaincontentalignment": false,
    "retainflexpositionproperties": false,
    "retainflowhorizontalalignment": false,
    "snapgridsize": 10,
    "snaptogrid": true,
    "tabpaneId": "tabSelfService",
    "wType": "FlexContainer",
    "widgetalignment": 1
}