{
    "classname": "transactionSigning",
    "definitions": {
        "apis": {
            "custom": [
                {
                    "group": "General",
                    "kuid": "e928aa0b961a4685af8c5f669940d186",
                    "paramList": [],
                    "propertyKey": "initiate",
                    "pw": {
                        "displayName": "initiate",
                        "uiRepresentation": "Label-Label-Button-Button"
                    },
                    "srcWgtKUID": "a4c6316cb0aa4c509b6bb332eb379120",
                    "type": "event"
                },
                {
                    "group": "General",
                    "kuid": "de2c11b93dd34601bdde61c730fd6145",
                    "paramList": [],
                    "propertyKey": "changeTSMode",
                    "pw": {
                        "displayName": "changeTSMode",
                        "uiRepresentation": "Label-Label-Button-Button"
                    },
                    "srcWgtKUID": "a4c6316cb0aa4c509b6bb332eb379120",
                    "type": "event"
                }
            ],
            "passthrough": []
        },
        "events": {
            "custom": [
                {
                    "group": "General",
                    "kuid": "i6c9bfda42e5420a85391d24f7ebe8b1",
                    "paramList": [],
                    "propertyIndex": 1,
                    "propertyKey": "showLoading",
                    "pw": {
                        "displayName": "showLoading",
                        "uiRepresentation": "Label-Label-Button-Button"
                    },
                    "srcWgtKUID": "a4c6316cb0aa4c509b6bb332eb379120",
                    "type": "event"
                },
                {
                    "group": "General",
                    "kuid": "ffe8938244334e90b92326e4c9b11a0f",
                    "paramList": [],
                    "propertyIndex": 2,
                    "propertyKey": "dismissLoading",
                    "pw": {
                        "displayName": "dismissLoading",
                        "uiRepresentation": "Label-Label-Button-Button"
                    },
                    "srcWgtKUID": "a4c6316cb0aa4c509b6bb332eb379120",
                    "type": "event"
                },
                {
                    "group": "General",
                    "kuid": "dd09b7c3e20b444b9ed1ef71585bbd34",
                    "paramList": [],
                    "propertyIndex": 3,
                    "propertyKey": "onTSSuccess",
                    "pw": {
                        "displayName": "onTSSuccess",
                        "uiRepresentation": "Label-Label-Button-Button"
                    },
                    "srcWgtKUID": "a4c6316cb0aa4c509b6bb332eb379120",
                    "type": "event"
                }
            ],
            "passthrough": []
        },
        "groups": {
            "apis": [
                "General"
            ],
            "events": [],
            "properties": [],
            "widgets": []
        },
        "properties": {
            "custom": [
                {
                    "access": "Write",
                    "defaultValue": "SyamTest1",
                    "group": "General",
                    "kuid": "d82bcbc98b97412da538dd7a2b3713f3",
                    "originalPropertyKey": "username",
                    "propertyIndex": 1,
                    "propertyKey": "username",
                    "pw": {
                        "dependencyConditions": {},
                        "displayName": "username",
                        "uiRepresentation": "Label-Textbox"
                    },
                    "srcWgtKUID": "a4c6316cb0aa4c509b6bb332eb379120",
                    "type": "string",
                    "value": ""
                },
                {
                    "access": "Write",
                    "defaultValue": "Sending amount transfers",
                    "group": "General",
                    "kuid": "e58df238fdc448719e5bfef13a1c9203",
                    "originalPropertyKey": "tds",
                    "propertyIndex": 2,
                    "propertyKey": "tds",
                    "pw": {
                        "dependencyConditions": {},
                        "displayName": "tds",
                        "uiRepresentation": "Label-Textbox"
                    },
                    "srcWgtKUID": "a4c6316cb0aa4c509b6bb332eb379120",
                    "type": "string",
                    "value": ""
                },
                {
                    "access": "Write",
                    "defaultValue": false,
                    "group": "General",
                    "kuid": "fa705f56339c4140969779eb811b0a67",
                    "originalPropertyKey": "isRMSEnabled",
                    "propertyIndex": 3,
                    "propertyKey": "isRMSEnabled",
                    "pw": {
                        "dependencyConditions": {},
                        "displayName": "isRMSEnabled",
                        "uiRepresentation": "Label-Radiobuttongroup"
                    },
                    "srcWgtKUID": "a4c6316cb0aa4c509b6bb332eb379120",
                    "type": "boolean",
                    "value": "true/false"
                },
                {
                    "access": "Write",
                    "defaultValue": 35,
                    "group": "General",
                    "kuid": "b6b840d45a454e6fb0a182e445f5bfee",
                    "originalPropertyKey": "thresholdAmount",
                    "propertyIndex": 4,
                    "propertyKey": "thresholdAmount",
                    "pw": {
                        "dependencyConditions": {},
                        "displayName": "thresholdAmount",
                        "type": "integer",
                        "uiRepresentation": "Label-Textbox",
                        "validationData": "^(\\+|-)?\\d+$"
                    },
                    "srcWgtKUID": "a4c6316cb0aa4c509b6bb332eb379120",
                    "type": "integer",
                    "value": ""
                },
                {
                    "access": "Write",
                    "defaultValue": "EUR",
                    "group": "General",
                    "kuid": "d2c1b4a1493440a285b0280d1c10da00",
                    "originalPropertyKey": "currency",
                    "propertyIndex": 5,
                    "propertyKey": "currency",
                    "pw": {
                        "dependencyConditions": {},
                        "displayName": "currency",
                        "uiRepresentation": "Label-Textbox"
                    },
                    "srcWgtKUID": "a4c6316cb0aa4c509b6bb332eb379120",
                    "type": "string",
                    "value": ""
                }
            ],
            "passthrough": [
                {
                    "access": "Enable",
                    "group": "General",
                    "kuid": "a5477eeb9f2a443f84e376ccf67adfc0",
                    "originalPropertyKey": "skin",
                    "propertyIndex": 8,
                    "propertyKey": "skin1",
                    "pw": {
                        "access": "readwrite",
                        "category": "skin",
                        "dependencyConditions": {},
                        "dependentKeysKUIDs": null,
                        "displayName": "Normal",
                        "isHiddenInTool": false,
                        "srcWidget": "flxPushDevices",
                        "wType": "FlexContainer"
                    },
                    "srcWgtKUID": "abf79cfb98dc49f7bd47bb2fe7dfcf02"
                }
            ]
        },
        "widgets": {
            "expose": [],
            "passthrough": []
        }
    },
    "namespace": "com.hid",
    "version": "1.0.0"
}