{
    "AS_Button_a9e2a8a76fdc4a68bb453fc2154d068e": {
        "id": "AS_Button_a9e2a8a76fdc4a68bb453fc2154d068e",
        "type": "ACTION_SEQUENCE",
        "params": [{
            "datatype": "collection",
            "name": "eventobject"
        }],
        "language": "js",
        "actions": [{
            "id": "INVOKE_FUNCTION__ide_onClick_bc6b6a62195a4711844aa6c97e59def6",
            "type": "INVOKE_FUNCTION",
            "sequenceKUID": "btnAdd_beneficiary",
            "display": "btnAdd_beneficiary",
            "inputparams": [],
            "callbackType": null,
            "disabled": null,
            "source": "controller"
        }]
    }
}