{
    "classname": "onboarding",
    "definitions": {
        "apis": {
            "custom": [
                {
                    "group": "General",
                    "kuid": "d9a63145d9f94a789a1e8e3f5e2c17df",
                    "paramList": [],
                    "propertyKey": "resetUI",
                    "pw": {
                        "displayName": "resetUI",
                        "uiRepresentation": "Label-Label-Button-Button"
                    },
                    "srcWgtKUID": "uf15ab3251854f83b8250c67bc31d319",
                    "type": "event"
                },
                {
                    "group": "General",
                    "kuid": "ef0cc16e83454a34888e4970af84925e",
                    "paramList": [],
                    "propertyKey": "getUserId",
                    "pw": {
                        "displayName": "getUserId",
                        "uiRepresentation": "Label-Label-Button-Button"
                    },
                    "srcWgtKUID": "uf15ab3251854f83b8250c67bc31d319",
                    "type": "event"
                }
            ],
            "passthrough": []
        },
        "events": {
            "custom": [
                {
                    "group": "General",
                    "kuid": "g29ac11e43fb41eca7fe0c39eb51b891",
                    "paramList": [],
                    "propertyIndex": 1,
                    "propertyKey": "showLoading",
                    "pw": {
                        "displayName": "showLoading",
                        "uiRepresentation": "Label-Label-Button-Button"
                    },
                    "srcWgtKUID": "uf15ab3251854f83b8250c67bc31d319",
                    "type": "event"
                },
                {
                    "group": "General",
                    "kuid": "a8f4565b2e1746a2941a79978f45d596",
                    "paramList": [],
                    "propertyIndex": 2,
                    "propertyKey": "dismissLoading",
                    "pw": {
                        "displayName": "dismissLoading",
                        "uiRepresentation": "Label-Label-Button-Button"
                    },
                    "srcWgtKUID": "uf15ab3251854f83b8250c67bc31d319",
                    "type": "event"
                },
                {
                    "group": "General",
                    "kuid": "jc45c8682f8442c78042a15c36064146",
                    "paramList": [],
                    "propertyIndex": 3,
                    "propertyKey": "changeContext",
                    "pw": {
                        "displayName": "changeContext",
                        "uiRepresentation": "Label-Label-Button-Button"
                    },
                    "srcWgtKUID": "uf15ab3251854f83b8250c67bc31d319",
                    "type": "event"
                },
                {
                    "group": "General",
                    "kuid": "da3a6984c46a4d68b19c166b633b6419",
                    "paramList": [],
                    "propertyIndex": 4,
                    "propertyKey": "switchLogin",
                    "pw": {
                        "displayName": "switchLogin",
                        "uiRepresentation": "Label-Label-Button-Button"
                    },
                    "srcWgtKUID": "uf15ab3251854f83b8250c67bc31d319",
                    "type": "event"
                },
                {
                    "group": "General",
                    "kuid": "f531fdc660254e57a9aab809081c9bf9",
                    "paramList": [],
                    "propertyIndex": 5,
                    "propertyKey": "passwordPolicy",
                    "pw": {
                        "displayName": "passwordPolicy",
                        "uiRepresentation": "Label-Label-Button-Button"
                    },
                    "srcWgtKUID": "uf15ab3251854f83b8250c67bc31d319",
                    "type": "event"
                }
            ],
            "passthrough": []
        },
        "groups": {
            "apis": [
                "General"
            ],
            "events": [],
            "properties": [],
            "widgets": []
        },
        "properties": {
            "custom": [
                {
                    "access": "Write",
                    "defaultValue": "FIDO",
                    "group": "General",
                    "kuid": "be8abb41bcc74fe49e712d08e54a08c7",
                    "originalPropertyKey": "FirstFactor",
                    "propertyIndex": 2,
                    "propertyKey": "FirstFactor",
                    "pw": {
                        "dependencyConditions": {},
                        "displayName": "FirstFactor",
                        "uiRepresentation": "Label-Combobox"
                    },
                    "srcWgtKUID": "uf15ab3251854f83b8250c67bc31d319",
                    "type": "list selector",
                    "value": [
                        "STATIC_PWD",
                        "SECURE_CODE",
                        "OTP_SMS_PIN",
                        "FIDO"
                    ]
                },
                {
                    "access": "Write",
                    "defaultValue": "NO_MFA",
                    "group": "General",
                    "kuid": "aa478d3acdf94debb803f2815346c3e2",
                    "originalPropertyKey": "MFA",
                    "propertyIndex": 3,
                    "propertyKey": "MFA",
                    "pw": {
                        "dependencyConditions": {},
                        "displayName": "MFA",
                        "uiRepresentation": "Label-Combobox"
                    },
                    "srcWgtKUID": "uf15ab3251854f83b8250c67bc31d319",
                    "type": "list selector",
                    "value": [
                        "APPROVE",
                        "OTP_SMS",
                        "OTP_EML",
                        "OTP_HWT",
                        "NO_MFA"
                    ]
                }
            ],
            "passthrough": []
        },
        "widgets": {
            "expose": [],
            "passthrough": []
        }
    },
    "namespace": "com.hid",
    "version": "1.0.0"
}