{
    "@class": "com.kony.gen.viz.model.container.KVizSegment2",
    "DNDConfig": null,
    "_bounces_": false,
    "_data_": [
        {},
        {},
        {},
        {},
        {},
        {},
        {},
        {},
        {},
        {}
    ],
    "_height_": {
        "type": "string",
        "value": "100%"
    },
    "_indicator_": "none",
    "_left_": {
        "type": "string",
        "value": "0dp"
    },
    "_margin_": [
        0,
        0,
        0,
        0
    ],
    "_orientation_": 2,
    "_padding_": [
        0,
        0,
        0,
        0
    ],
    "_top_": {
        "type": "string",
        "value": "0dp"
    },
    "_width_": {
        "type": "string",
        "value": "100%"
    },
    "autogrowmode": 0,
    "canUpdateUI": true,
    "containerweight": 100,
    "counter": "01",
    "focusedindex": null,
    "focuseditem": null,
    "groupcells": false,
    "hasSections": false,
    "id": "segUsers",
    "info": null,
    "ipad": {
        "psp": {
            "indicator": "rowselect"
        }
    },
    "iphone": {
        "psp": {
            "bounces": false,
            "indicator": "none",
            "showProgressIndicator": false
        }
    },
    "iscustomlayout": false,
    "isvisible": true,
    "kuid": "h8d55a9e4f404073bab991a959dbcaec",
    "masterdata": {},
    "mobile": {
        "_data_": [
            {
                "Label0e1e8c911738b41": {
                    "@class": "com.viz.ide.model.segment.SimpleTextSegmentData",
                    "text": ""
                },
                "TrashDark": {
                    "@class": "com.viz.ide.model.segment.SimpleTextSegmentData",
                    "text": ""
                },
                "imgAvatar": {
                    "@class": "com.viz.ide.model.segment.ImageSegmentData",
                    "src": ""
                },
                "lblUsername": {
                    "@class": "com.viz.ide.model.segment.SimpleTextSegmentData",
                    "text": ""
                }
            },
            {
                "Label0e1e8c911738b41": {
                    "@class": "com.viz.ide.model.segment.SimpleTextSegmentData",
                    "text": ""
                },
                "TrashDark": {
                    "@class": "com.viz.ide.model.segment.SimpleTextSegmentData",
                    "text": ""
                },
                "imgAvatar": {
                    "@class": "com.viz.ide.model.segment.ImageSegmentData",
                    "src": ""
                },
                "lblUsername": {
                    "@class": "com.viz.ide.model.segment.SimpleTextSegmentData",
                    "text": ""
                }
            }
        ],
        "rowTemplateId": "hd62c9e691dc4e3ba856189c22dd3487",
        "rowtemplate": "CopyflxHIDUsersTemplate",
        "widgetdatamap": {
            "CopyflxHIDUsersTemplate": "CopyflxHIDUsersTemplate",
            "Label0e1e8c911738b41": "Label0e1e8c911738b41",
            "TrashDark": "TrashDark",
            "flxContactImg": "flxContactImg",
            "flxDelRow": "flxDelRow",
            "flxRowWrapper": "flxRowWrapper",
            "flxTempRowWrapper": "flxTempRowWrapper",
            "imgAvatar": "imgAvatar",
            "lblUsername": "lblUsername"
        }
    },
    "name": "kony.ui.SegmentedUI2",
    "needpageindicator": true,
    "pageoffdotimage": "pageoffdot.png",
    "pageondotimage": "pageondot.png",
    "paginationconfig": {
        "position": "bottom"
    },
    "parent": "flxScrollUsers",
    "pf": "userwidgetmodel",
    "retaincontentalignment": false,
    "retainflexpositionproperties": false,
    "retainselection": false,
    "rowcounter": 1,
    "rowfocusskin": "sc7e34ba70a64c0c9bd178e3b14b51a7",
    "rowskin": "s2b99621c6144439b5c5dd4bb0e57266",
    "rowtemplate": null,
    "screenlevelwidget": false,
    "seccounter": 0,
    "sectionheaderskin": "se3e2f70dddc4f0ab77ea7f34882169a",
    "selectedRows": null,
    "selectedState": false,
    "selectedindex": null,
    "selectedindices": null,
    "selecteditems": null,
    "selectedsectionindex": 0,
    "selectionbehavior": "default",
    "separatorcolor": "f2f2f200",
    "separatorrequired": true,
    "separatorthickness": 3,
    "showscrollbars": false,
    "viewtype": "tableview",
    "vizProps": {},
    "wType": "Segment",
    "widgetalignment": 5,
    "widgetdatamap": {
        "CopyflxHIDUsersTemplate": "CopyflxHIDUsersTemplate",
        "imgAvatar": "imgAvatar",
        "lblUsername": "lblUsername"
    },
    "zindex": 40
}