{
    "@class": "com.kony.gen.viz.model.component.KVizTextBox2",
    "DNDConfig": null,
    "_height_": {
        "type": "string",
        "value": "100%"
    },
    "_left_": {
        "type": "string",
        "value": "5%"
    },
    "_margin_": [
        0,
        0,
        0,
        0
    ],
    "_padding_": [
        3,
        0,
        0,
        0
    ],
    "_placeholder_": "User ID",
    "_skin_": "s3ccb753eb354d6b920f6e12611e8fae",
    "_text_": "",
    "_top_": {
        "type": "string",
        "value": "9dp"
    },
    "_width_": {
        "type": "string",
        "value": "90%"
    },
    "autocapitalize": "none",
    "autocomplete": false,
    "autocorrect": false,
    "autofilter": false,
    "canUpdateUI": true,
    "centery": {
        "type": "string",
        "value": "50%"
    },
    "containerheight": "",
    "containerheightmode": 1,
    "containerweight": 100,
    "contentalignment": 4,
    "desktopweb": {
        "placeholderSkin": "sc96115ec6034e7d837bad9b640ba1c3"
    },
    "disabledSkins": {
        "focusSkin": "s271e105b7054d32ac88d623c1b4baff"
    },
    "focusskin": null,
    "id": "textUserId",
    "info": null,
    "iscustomlayout": false,
    "isvisible": true,
    "keyboardtype": "A",
    "kuid": "uae7624763a24486bf7d02c66f061989",
    "mode": "A",
    "name": "kony.ui.TextBox2",
    "parent": "userid",
    "pf": "userwidgetmodel",
    "placeholderskin": "sc96115ec6034e7d837bad9b640ba1c3",
    "retaincontentalignment": false,
    "retainflexpositionproperties": false,
    "securetextentry": false,
    "textinputmode": "A",
    "tooltip": "",
    "viewtype": "default",
    "wType": "TextField",
    "zindex": 1
}