{
    "@class": "com.kony.gen.viz.model.component.KVizLabel",
    "DNDConfig": null,
    "_height_": {
        "type": "string",
        "value": "30%"
    },
    "_left_": {
        "type": "string",
        "value": "0%"
    },
    "_margin_": [
        0,
        0,
        0,
        0
    ],
    "_padding_": [
        0,
        0,
        0,
        0
    ],
    "_skin_": "s6b2e07a49c34bdf9fe6b01abf2407b6",
    "_text_": "Current PIN",
    "_top_": {
        "type": "string",
        "value": "0%"
    },
    "_width_": {
        "type": "ref",
        "value": "preferred"
    },
    "_wrapping_": 2,
    "android": {
        "textStyle": {
            "letterSpacing": "-0.1875",
            "lineSpacing": 0,
            "strikeThrough": false
        }
    },
    "canUpdateUI": true,
    "containerweight": 100,
    "contentalignment": 4,
    "focusskin": "sb842168be4c4a35940bf56194937390",
    "id": "lblCurrentPINInner",
    "info": null,
    "ipad": {
        "psp": {
            "wrapping": 2
        },
        "textStyle": {
            "baseline": 0,
            "letterSpacing": "-0.1875",
            "lineSpacing": 0,
            "strikeThrough": false
        }
    },
    "iphone": {
        "psp": {
            "wrapping": 2
        },
        "textStyle": {
            "baseline": 0,
            "letterSpacing": "-0.1875",
            "lineSpacing": 0,
            "strikeThrough": false
        }
    },
    "isvisible": true,
    "kuid": "c473b7666582432188c36d09d6724b84",
    "name": "kony.ui.Label",
    "parent": "flxCurrentPINInner",
    "pf": "userwidgetmodel",
    "textstyle": {},
    "tooltip": "",
    "wType": "Label",
    "zindex": 1
}