{
    "@class": "com.kony.gen.viz.model.component.KVizButton",
    "DNDConfig": null,
    "_height_": {
        "type": "string",
        "value": "100%"
    },
    "_left_": {
        "type": "string",
        "value": "4%"
    },
    "_margin_": [
        6,
        6,
        6,
        6
    ],
    "_padding_": [
        0,
        0,
        0,
        0
    ],
    "_skin_": "sa02904431704721a32205eaa8b8734f",
    "_text_": "Cancel",
    "_top_": {
        "type": "string",
        "value": "0%"
    },
    "_width_": {
        "type": "string",
        "value": "48%"
    },
    "canUpdateUI": true,
    "centery": {
        "type": "number",
        "value": ""
    },
    "containerweight": 100,
    "contentalignment": 5,
    "displaytext": true,
    "focusskin": "s6b1e2fc8e3c4117886fc0d56c4876a4",
    "id": "btnCancelPush",
    "ide_onClick": "AS_Button_ddfb51a0bf4a4d4db7c0b0a77113abf1",
    "info": null,
    "iscustomlayout": false,
    "isvisible": true,
    "kuid": "ua929eba396f49508849b93b68b70665",
    "name": "kony.ui.Button",
    "parent": "flxPushApproveBtn",
    "pf": "userwidgetmodel",
    "retaincontentalignment": false,
    "retainflexpositionproperties": false,
    "wType": "Button",
    "zindex": 1
}