{
    "@class": "com.kony.gen.viz.model.component.KVizButton",
    "DNDConfig": null,
    "_height_": {
        "type": "string",
        "value": "100%"
    },
    "_left_": {
        "type": "string",
        "value": "0%"
    },
    "_margin_": [
        6,
        6,
        6,
        6
    ],
    "_padding_": [
        0,
        0,
        0,
        0
    ],
    "_skin_": "s62c06c9d97a409a9244f4a5c4e199c9",
    "_text_": "LOGIN",
    "_top_": {
        "type": "string",
        "value": "0%"
    },
    "_width_": {
        "type": "string",
        "value": "100%"
    },
    "canUpdateUI": true,
    "centerx": {
        "type": "string",
        "value": "50%"
    },
    "centery": {
        "type": "number",
        "value": ""
    },
    "containerweight": 100,
    "contentalignment": 5,
    "desktopweb": {
        "blockedUISkin": "sb4052daabfa44a08fe8db0819e055cb"
    },
    "disabledSkins": {},
    "displaytext": true,
    "focusskin": "s43268be1bbd4abbb8df6d259924ff41",
    "id": "btnLoginSecure",
    "ide_onClick": "AS_Button_c0571ca786f14b69abf3527f4774f6f0",
    "info": null,
    "iscustomlayout": false,
    "isvisible": true,
    "kuid": "ue413294919140febf3db447e1f5d3c4",
    "name": "kony.ui.Button",
    "parent": "flxButtonsSecure",
    "pf": "userwidgetmodel",
    "retaincontentalignment": false,
    "retainflexpositionproperties": false,
    "wType": "Button",
    "zindex": 1
}