{
    "classname": "qrcodegenerator",
    "definitions": {
        "apis": {
            "custom": [
                {
                    "group": "General",
                    "kuid": "cb6789c875464efe8ede482cac8a4fb9",
                    "paramList": [],
                    "propertyKey": "generate",
                    "pw": {
                        "displayName": "generate",
                        "uiRepresentation": "Label-Label-Button-Button"
                    },
                    "srcWgtKUID": "ie2ce5bd9888444e8400947e44244542",
                    "type": "event"
                }
            ],
            "passthrough": []
        },
        "events": {
            "custom": [],
            "passthrough": []
        },
        "groups": {
            "apis": [
                "General"
            ],
            "events": [],
            "properties": [],
            "widgets": []
        },
        "properties": {
            "custom": [
                {
                    "access": "Write",
                    "defaultValue": "kony",
                    "group": "General",
                    "kuid": "i875caf495744c7ebd4f3eebfe6fa70b",
                    "originalPropertyKey": "dataToEncode",
                    "propertyIndex": 1,
                    "propertyKey": "dataToEncode",
                    "pw": {
                        "displayName": "Data To Encode",
                        "uiRepresentation": "Label-Textbox"
                    },
                    "srcWgtKUID": "ie2ce5bd9888444e8400947e44244542",
                    "type": "string",
                    "value": ""
                },
                {
                    "access": "Write",
                    "defaultValue": "#000000",
                    "group": "General",
                    "kuid": "h5aafa2b9a4540da8caec36d00dff2a6",
                    "originalPropertyKey": "colorLight",
                    "propertyIndex": 2,
                    "propertyKey": "colorLight",
                    "pw": {
                        "displayName": "Color Light",
                        "uiRepresentation": "Label-Textbox"
                    },
                    "srcWgtKUID": "ie2ce5bd9888444e8400947e44244542",
                    "type": "string",
                    "value": ""
                },
                {
                    "access": "Write",
                    "defaultValue": "#00539b",
                    "group": "General",
                    "kuid": "g66c286c6f0041aa8b24ae0cff35a178",
                    "originalPropertyKey": "colorDark",
                    "propertyIndex": 3,
                    "propertyKey": "colorDark",
                    "pw": {
                        "displayName": "Color Dark",
                        "uiRepresentation": "Label-Textbox"
                    },
                    "srcWgtKUID": "ie2ce5bd9888444e8400947e44244542",
                    "type": "string",
                    "value": ""
                },
                {
                    "access": "Write",
                    "defaultValue": "140",
                    "group": "General",
                    "kuid": "h89845db4cd1438abe873d1b8a0d6152",
                    "originalPropertyKey": "qrcodeWidth",
                    "propertyIndex": 4,
                    "propertyKey": "qrcodeWidth",
                    "pw": {
                        "displayName": "QR Code Width",
                        "uiRepresentation": "Label-Textbox"
                    },
                    "srcWgtKUID": "ie2ce5bd9888444e8400947e44244542",
                    "type": "string",
                    "value": ""
                },
                {
                    "access": "Write",
                    "defaultValue": "140",
                    "group": "General",
                    "kuid": "b3dcafcbee9c43528d960acec9530e0a",
                    "originalPropertyKey": "qrcodeHeight",
                    "propertyIndex": 5,
                    "propertyKey": "qrcodeHeight",
                    "pw": {
                        "displayName": "QR Code Height",
                        "uiRepresentation": "Label-Textbox"
                    },
                    "srcWgtKUID": "ie2ce5bd9888444e8400947e44244542",
                    "type": "string",
                    "value": ""
                },
                {
                    "access": "Write",
                    "defaultValue": "Level M",
                    "group": "General",
                    "kuid": "g523f30e11cc42ca909ece77047aaa6d",
                    "originalPropertyKey": "correctLevel",
                    "propertyIndex": 6,
                    "propertyKey": "correctLevel",
                    "pw": {
                        "displayName": "Error Correction Level",
                        "uiRepresentation": "Label-Combobox"
                    },
                    "srcWgtKUID": "ie2ce5bd9888444e8400947e44244542",
                    "type": "list selector",
                    "value": [
                        "Level L",
                        "Level M",
                        "Level Q",
                        "Level H"
                    ]
                }
            ],
            "passthrough": []
        },
        "widgets": {
            "expose": [],
            "passthrough": []
        }
    },
    "namespace": "com.konymp",
    "version": "1.0.0"
}